[{"t": 90, "n": "ביר הדאג'", "i": "173"}, {"t": 60, "n": "מנחמיה", "i": "756"}, {"t": 60, "n": "גבעת ישעיהו", "i": "302"}, {"t": 60, "n": "גשר", "i": "355"}, {"t": 0, "n": "מנרה", "i": "758"}, {"t": 90, "n": "פני קדם", "i": "1060"}, {"t": 60, "n": "טמרה בגלבוע", "i": "493"}, {"t": 90, "n": "כרמים", "i": "667"}, {"t": 30, "n": "הודיה", "i": "386"}, {"t": 90, "n": "אלקנה", "i": "126"}, {"t": 0, "n": "מנות", "i": "755"}, {"t": 0, "n": "חספין", "i": "463"}, {"t": 60, "n": "שדות מיכה", "i": "1215"}, {"t": 90, "n": "גבעת חביבה", "i": "297"}, {"t": 60, "n": "עצמון - שגב", "i": "1035"}, {"t": 90, "n": "מדרך עוז", "i": "714"}, {"t": 90, "n": "תרום", "i": "1306"}, {"t": 60, "n": "אזור תעשייה אלון התבור", "i": "1362"}, {"t": 60, "n": "הבונים", "i": "382"}, {"t": 90, "n": "ייט''ב", "i": "518"}, {"t": 15, "n": "מבטחים, עמיעוז, ישע", "i": "697"}, {"t": 60, "n": "ניר עציון", "i": "910"}, {"t": 60, "n": "דיר חנא", "i": "371"}, {"t": 60, "n": "בית אלפא וחפציבה", "i": "1308"}, {"t": 90, "n": "עין שמר", "i": "1010"}, {"t": 90, "n": "עין עירון", "i": "1006"}, {"t": 60, "n": "שדה אליהו", "i": "1200"}, {"t": 90, "n": "נעורים", "i": "919"}, {"t": 90, "n": "אזור תעשייה כפר יונה", "i": "1405"}, {"t": 90, "n": "כפר ברא", "i": "588"}, {"t": 90, "n": "יד חנה", "i": "504"}, {"t": 60, "n": "לקיה", "i": "687"}, {"t": 90, "n": "נען", "i": "922"}, {"t": 60, "n": "נווה אור", "i": "855"}, {"t": 60, "n": "עין הוד", "i": "988"}, {"t": 90, "n": "בני עטרות", "i": "243"}, {"t": 90, "n": "פארק תעשיות פלמחים", "i": "1047"}, {"t": 90, "n": "ענב", "i": "1030"}, {"t": 0, "n": "הילה", "i": "392"}, {"t": 45, "n": "אורות", "i": "36"}, {"t": 90, "n": "כפר שמואל", "i": "651"}, {"t": 90, "n": "צומת הגוש", "i": "1444"}, {"t": 90, "n": "נווה זוהר", "i": "860"}, {"t": 90, "n": "אבן יהודה", "i": "12"}, {"t": 0, "n": "סאסא", "i": "936"}, {"t": 60, "n": "כחל", "i": "563"}, {"t": 0, "n": "יפתח", "i": "533"}, {"t": 90, "n": "כפר מל''ל", "i": "629"}, {"t": 90, "n": "נווה חריף", "i": "862"}, {"t": 60, "n": "עינבר", "i": "1013"}, {"t": 90, "n": "העוגן", "i": "397"}, {"t": 90, "n": "זכרון יעקב", "i": "416"}, {"t": 90, "n": "קריית יערים", "i": "1123"}, {"t": 90, "n": "בחן", "i": "169"}, {"t": 90, "n": "מקווה ישראל", "i": "806"}, {"t": 45, "n": "בני דרום", "i": "239"}, {"t": 90, "n": "שגב שלום", "i": "1197"}, {"t": 90, "n": "מאור", "i": "688"}, {"t": 30, "n": "אבן שמואל", "i": "15"}, {"t": 90, "n": "בית חרות", "i": "200"}, {"t": 90, "n": "כושי רמון", "i": "562"}, {"t": 60, "n": "כאבול", "i": "552"}, {"t": 60, "n": "אזור תעשייה ניר עציון", "i": "60"}, {"t": 90, "n": "משמרות", "i": "831"}, {"t": 90, "n": "ראשון לציון - מזרח", "i": "6025"}, {"t": 90, "n": "ראשון לציון - מערב", "i": "6026"}, {"t": 60, "n": "טמרה", "i": "492"}, {"t": 15, "n": "כפר ורדים", "i": "607"}, {"t": 90, "n": "יצהר", "i": "534"}, {"t": 60, "n": "סואעד חמירה", "i": "939"}, {"t": 90, "n": "מעלה עירון", "i": "786"}, {"t": 90, "n": "חמד", "i": "455"}, {"t": 90, "n": "רשפון", "i": "1187"}, {"t": 45, "n": "אזור תעשייה עידן הנגב", "i": "63"}, {"t": 90, "n": "מצפה אילן", "i": "800"}, {"t": 30, "n": "כפר מסריק", "i": "632"}, {"t": 90, "n": "נבטים", "i": "845"}, {"t": 60, "n": "יפיע", "i": "530"}, {"t": 90, "n": "גני תקווה", "i": "348"}, {"t": 90, "n": "ארסוף", "i": "142"}, {"t": 90, "n": "גבעת זאב", "i": "296"}, {"t": 90, "n": "אור יהודה", "i": "33"}, {"t": 90, "n": "מעלה החמישה", "i": "782"}, {"t": 60, "n": "כינרת מושבה", "i": "564"}, {"t": 90, "n": "חרוצים", "i": "471"}, {"t": 60, "n": "גבעת אלה", "i": "291"}, {"t": 90, "n": "לוטן", "i": "681"}, {"t": 90, "n": "אזור תעשייה מישור אדומים", "i": "1360"}, {"t": 90, "n": "אלעד", "i": "122"}, {"t": 90, "n": "טירת יהודה", "i": "484"}, {"t": 60, "n": "גבעת וושינגטון", "i": "295"}, {"t": 90, "n": "תל ערד", "i": "1377"}, {"t": 15, "n": "חד נס", "i": "431"}, {"t": 0, "n": "אילון", "i": "90"}, {"t": 90, "n": "כפר בן נון", "i": "587"}, {"t": 30, "n": "עכו - כל האזורים", "i": "7FF3828F531B759EDA5F1D96B166C601"}, {"t": 30, "n": "לפידות", "i": "686"}, {"t": 90, "n": "תל ציון", "i": "1284"}, {"t": 90, "n": "אזור תעשייה חבל מודיעין", "i": "1361"}, {"t": 90, "n": "נחם", "i": "884"}, {"t": 60, "n": "מפעל אגריגדה", "i": "1434"}, {"t": 60, "n": "קריית ביאליק - כל האזורים", "i": "5DCF27C662653F9D7CB79C995B5121B1"}, {"t": 90, "n": "הר גילה", "i": "401"}, {"t": 90, "n": "עמנואל", "i": "1028"}, {"t": 60, "n": "החותרים", "i": "390"}, {"t": 90, "n": "גבעת יערים", "i": "301"}, {"t": 90, "n": "ירוחם", "i": "542"}, {"t": 90, "n": "כרם רעים", "i": "1432"}, {"t": 60, "n": "כפר תקווה", "i": "655"}, {"t": 30, "n": "אזור תעשייה שחורת", "i": "74"}, {"t": 90, "n": "טל מנשה", "i": "488"}, {"t": 90, "n": "יפית", "i": "531"}, {"t": 90, "n": "שוהם", "i": "1222"}, {"t": 60, "n": "ראס עלי", "i": "1137"}, {"t": 90, "n": "חניאל", "i": "460"}, {"t": 90, "n": "ירקונה", "i": "545"}, {"t": 0, "n": "כפר בלום", "i": "586"}, {"t": 0, "n": "ג'ש - גוש חלב", "i": "277"}, {"t": 90, "n": "כפר קרע", "i": "647"}, {"t": 15, "n": "חוף סוסיתא", "i": "1425"}, {"t": 45, "n": "אזור תעשייה עד הלום", "i": "62"}, {"t": 90, "n": "בקעות", "i": "254"}, {"t": 90, "n": "נווה שלום", "i": "868"}, {"t": 90, "n": "הר ברכה", "i": "400"}, {"t": 90, "n": "צור הדסה", "i": "1081"}, {"t": 45, "n": "בית עזרא", "i": "220"}, {"t": 15, "n": "גברעם", "i": "311"}, {"t": 30, "n": "נוגה", "i": "853"}, {"t": 90, "n": "חלמיש", "i": "453"}, {"t": 60, "n": "בני דקלים", "i": "238"}, {"t": 30, "n": "תדהר", "i": "1272"}, {"t": 90, "n": "טנא עומרים", "i": "494"}, {"t": 45, "n": "גבעתי", "i": "309"}, {"t": 60, "n": "שריד", "i": "1267"}, {"t": 90, "n": "חרות", "i": "472"}, {"t": 90, "n": "מי עמי", "i": "740"}, {"t": 60, "n": "גניגר", "i": "349"}, {"t": 90, "n": "צופר", "i": "1079"}, {"t": 30, "n": "ברוש", "i": "259"}, {"t": 45, "n": "שדה משה", "i": "1208"}, {"t": 30, "n": "באר גנים", "i": "158"}, {"t": 90, "n": "מעלה רחבעם", "i": "1375"}, {"t": 90, "n": "רימונים", "i": "1163"}, {"t": 0, "n": "עין זיוון", "i": "996"}, {"t": 30, "n": "כוכב מיכאל", "i": "560"}, {"t": 0, "n": "משגב עם", "i": "819"}, {"t": 45, "n": "ניצן", "i": "1344"}, {"t": 90, "n": "צור משה", "i": "1083"}, {"t": 15, "n": "קדמת צבי", "i": "1100"}, {"t": 30, "n": "שער הגולן", "i": "1255"}, {"t": 45, "n": "שדה עוזיהו", "i": "1212"}, {"t": 90, "n": "כוכב יאיר - צור יגאל", "i": "558"}, {"t": 90, "n": "בית חנן", "i": "198"}, {"t": 90, "n": "להבות חביבה", "i": "675"}, {"t": 0, "n": "אזור תעשייה בני יהודה", "i": "45"}, {"t": 60, "n": "קריית אתא", "i": "1130"}, {"t": 90, "n": "עופרים", "i": "968"}, {"t": 0, "n": "כפר גלעדי", "i": "593"}, {"t": 30, "n": "זוהר", "i": "413"}, {"t": 90, "n": "מעיין צבי", "i": "776"}, {"t": 90, "n": "אל סייד", "i": "1374"}, {"t": 90, "n": "ספיר", "i": "952"}, {"t": 90, "n": "שואבה", "i": "1223"}, {"t": 30, "n": "עין כמונים", "i": "1002"}, {"t": 90, "n": "עתניאל", "i": "1045"}, {"t": 90, "n": "כפר ידידיה", "i": "618"}, {"t": 30, "n": "סאג'ור", "i": "935"}, {"t": 0, "n": "אבן מנחם", "i": "13"}, {"t": 15, "n": "כפר מימון ותושיה", "i": "1336"}, {"t": 60, "n": "גדעונה", "i": "314"}, {"t": 0, "n": "גשר הזיו", "i": "356"}, {"t": 30, "n": "מנחת מחניים", "i": "757"}, {"t": 30, "n": "שדה צבי", "i": "1213"}, {"t": 90, "n": "עין העמק", "i": "992"}, {"t": 90, "n": "נווה דניאל", "i": "859"}, {"t": 90, "n": "גיתית", "i": "328"}, {"t": 45, "n": "נחלה", "i": "881"}, {"t": 90, "n": "רגבים", "i": "1147"}, {"t": 15, "n": "דקל", "i": "379"}, {"t": 90, "n": "מכון וינגייט", "i": "748"}, {"t": 90, "n": "אלישיב", "i": "118"}, {"t": 15, "n": "ניר יצחק", "i": "905"}, {"t": 90, "n": "סמר", "i": "947"}, {"t": 60, "n": "אכסאל", "i": "97"}, {"t": 90, "n": "בית חנניה", "i": "199"}, {"t": 90, "n": "חוות יאיר", "i": "433"}, {"t": 60, "n": "באר שבע - דרום", "i": "6004"}, {"t": 60, "n": "באר שבע - מזרח", "i": "6005"}, {"t": 60, "n": "באר שבע - מערב", "i": "6006"}, {"t": 60, "n": "באר שבע - צפון", "i": "6007"}, {"t": 90, "n": "אזור תעשייה יקנעם עילית", "i": "54"}, {"t": 15, "n": "רמות", "i": "1167"}, {"t": 30, "n": "חרשים", "i": "476"}, {"t": 60, "n": "רמת צבי", "i": "1181"}, {"t": 90, "n": "רותם", "i": "1155"}, {"t": 90, "n": "מחולה", "i": "735"}, {"t": 30, "n": "מבקיעים", "i": "698"}, {"t": 90, "n": "צופים", "i": "1077"}, {"t": 90, "n": "גבעות", "i": "287"}, {"t": 15, "n": "מבטחים, עמיעוז, ישע", "i": "1315"}, {"t": 60, "n": "מזרע", "i": "733"}, {"t": 15, "n": "נהריה", "i": "851"}, {"t": 30, "n": "צאלים", "i": "1073"}, {"t": 60, "n": "ארבל", "i": "138"}, {"t": 60, "n": "מע'אר", "i": "766"}, {"t": 60, "n": "כפר כמא", "i": "624"}, {"t": 90, "n": "אדרת", "i": "22"}, {"t": 90, "n": "יציץ", "i": "535"}, {"t": 0, "n": "מרום גולן", "i": "808"}, {"t": 30, "n": "עין המפרץ", "i": "990"}, {"t": 90, "n": "נווה ימין", "i": "864"}, {"t": 90, "n": "שער אפרים", "i": "1254"}, {"t": 90, "n": "הדר עם", "i": "384"}, {"t": 90, "n": "אלון שבות", "i": "107"}, {"t": 90, "n": "יקנעם המושבה והזורע", "i": "538"}, {"t": 60, "n": "דחי", "i": "368"}, {"t": 0, "n": "פסוטה", "i": "1063"}, {"t": 0, "n": "מטולה", "i": "738"}, {"t": 90, "n": "אמץ", "i": "130"}, {"t": 90, "n": "תל אביב - דרום העיר ויפו", "i": "6029"}, {"t": 90, "n": "תל אביב - מזרח", "i": "6030"}, {"t": 90, "n": "תל אביב - מרכז העיר", "i": "6031"}, {"t": 90, "n": "תל אביב - עבר הירקון", "i": "6032"}, {"t": 60, "n": "מעוז חיים", "i": "771"}, {"t": 45, "n": "קדמה", "i": "1099"}, {"t": 60, "n": "כפר מרדכי", "i": "633"}, {"t": 60, "n": "בית עלמין תל רגב", "i": "221"}, {"t": 90, "n": "משמר העמק", "i": "828"}, {"t": 60, "n": "כמהין", "i": "572"}, {"t": 90, "n": "שאנטי במדבר", "i": "1190"}, {"t": 90, "n": "שדמות מחולה", "i": "1220"}, {"t": 90, "n": "אדוריים", "i": "1365"}, {"t": 90, "n": "כפר הרא''ה", "i": "603"}, {"t": 90, "n": "אזור", "i": "42"}, {"t": 60, "n": "שריגים - לי-און", "i": "1266"}, {"t": 90, "n": "חי-בר יטבתה", "i": "450"}, {"t": 90, "n": "אלישמע", "i": "119"}, {"t": 60, "n": "נורית", "i": "878"}, {"t": 90, "n": "רמת רזיאל", "i": "1182"}, {"t": 90, "n": "בית ינאי", "i": "204"}, {"t": 90, "n": "כפר תפוח", "i": "654"}, {"t": 0, "n": "זרעית", "i": "424"}, {"t": 90, "n": "זיתן", "i": "415"}, {"t": 0, "n": "אלי עד", "i": "112"}, {"t": 60, "n": "צרופה", "i": "1093"}, {"t": 90, "n": "עפרה", "i": "1033"}, {"t": 30, "n": "חוף אמנון", "i": "1417"}, {"t": 90, "n": "נירית", "i": "914"}, {"t": 90, "n": "ראש צורים", "i": "1141"}, {"t": 90, "n": "בית חג\"י", "i": "194"}, {"t": 60, "n": "עילוט", "i": "979"}, {"t": 60, "n": "מסד", "i": "760"}, {"t": 90, "n": "נווה מיכאל - רוגלית", "i": "867"}, {"t": 90, "n": "אורון תעשייה ומסחר", "i": "1384"}, {"t": 60, "n": "ישובי יעל", "i": "1323"}, {"t": 60, "n": "דור", "i": "366"}, {"t": 15, "n": "יושיביה", "i": "514"}, {"t": 90, "n": "עיינות", "i": "977"}, {"t": 90, "n": "מעלה מכמש", "i": "785"}, {"t": 90, "n": "שפיים", "i": "1259"}, {"t": 0, "n": "מעלות תרשיחא", "i": "790"}, {"t": 30, "n": "נתיבות", "i": "934"}, {"t": 15, "n": "ניר עוז", "i": "908"}, {"t": 0, "n": "מרכז אזורי מבואות חרמון", "i": "1355"}, {"t": 15, "n": "געתון", "i": "351"}, {"t": 90, "n": "נערן", "i": "923"}, {"t": 60, "n": "ישובי יעל", "i": "1340"}, {"t": 90, "n": "כפר האורנים", "i": "596"}, {"t": 90, "n": "ממשית", "i": "1370"}, {"t": 45, "n": "אביגדור", "i": "8"}, {"t": 60, "n": "שער העמקים", "i": "1256"}, {"t": 30, "n": "ניר ח''ן", "i": "904"}, {"t": 90, "n": "כפר גליקסון", "i": "592"}, {"t": 90, "n": "אל פורעה", "i": "380"}, {"t": 90, "n": "צור יצחק", "i": "1082"}, {"t": 60, "n": "אזור תעשייה טמרה", "i": "1404"}, {"t": 90, "n": "גבעתיים", "i": "310"}, {"t": 60, "n": "תחנת רכבת כפר ברוך", "i": "1447"}, {"t": 90, "n": "גבעת הראל וגבעת הרואה", "i": "1367"}, {"t": 45, "n": "אתר דודאים", "i": "1391"}, {"t": 30, "n": "רוחמה", "i": "1151"}, {"t": 90, "n": "נחלים", "i": "883"}, {"t": 90, "n": "אביעזר", "i": "10"}, {"t": 90, "n": "נורדיה", "i": "877"}, {"t": 90, "n": "מעלה לבונה", "i": "784"}, {"t": 90, "n": "בית הלוי", "i": "186"}, {"t": 90, "n": "נאות חובב", "i": "2183"}, {"t": 90, "n": "פתח תקווה", "i": "1071"}, {"t": 90, "n": "נחליאל", "i": "882"}, {"t": 30, "n": "איילת השחר", "i": "89"}, {"t": 90, "n": "בית הערבה", "i": "189"}, {"t": 60, "n": "גני טל", "i": "345"}, {"t": 90, "n": "רתמים", "i": "1189"}, {"t": 90, "n": "מתחם שביל התפוזים", "i": "2203"}, {"t": 45, "n": "אופקים", "i": "30"}, {"t": 15, "n": "ארז", "i": "140"}, {"t": 90, "n": "מגדלים", "i": "707"}, {"t": 0, "n": "ע'ג'ר", "i": "958"}, {"t": 60, "n": "סכנין", "i": "943"}, {"t": 90, "n": "נחשונים", "i": "888"}, {"t": 30, "n": "צפת - נוף כנרת", "i": "6100"}, {"t": 30, "n": "צפת - עיר", "i": "6101"}, {"t": 30, "n": "צפת - עכברה", "i": "6102"}, {"t": 30, "n": "מעגן", "i": "769"}, {"t": 90, "n": "המעפיל", "i": "394"}, {"t": 60, "n": "גדרה", "i": "315"}, {"t": 90, "n": "מגל", "i": "709"}, {"t": 90, "n": "בארותיים", "i": "163"}, {"t": 90, "n": "חופית", "i": "444"}, {"t": 90, "n": "מודיעין - ליגד סנטר", "i": "718"}, {"t": 90, "n": "חדיד", "i": "432"}, {"t": 60, "n": "כפר יחזקאל", "i": "621"}, {"t": 90, "n": "טייבה", "i": "481"}, {"t": 90, "n": "מחסיה", "i": "737"}, {"t": 45, "n": "אמונים", "i": "127"}, {"t": 90, "n": "אום בטין", "i": "29"}, {"t": 45, "n": "גת", "i": "357"}, {"t": 30, "n": "ראש פינה", "i": "1140"}, {"t": 90, "n": "נבי סמואל", "i": "846"}, {"t": 30, "n": "תלמי ביל''ו", "i": "1291"}, {"t": 60, "n": "אזור תעשייה כנות", "i": "55"}, {"t": 90, "n": "ירושלים - אזור תעשייה עטרות", "i": "6038"}, {"t": 90, "n": "ירושלים - דרום", "i": "6018"}, {"t": 90, "n": "ירושלים - כפר עקב", "i": "6036"}, {"t": 90, "n": "ירושלים - מזרח", "i": "6019"}, {"t": 90, "n": "ירושלים - מערב", "i": "6021"}, {"t": 90, "n": "ירושלים - מרכז", "i": "6022"}, {"t": 90, "n": "ירושלים - צפון", "i": "6020"}, {"t": 15, "n": "אבשלום", "i": "19"}, {"t": 60, "n": "בית השיטה", "i": "190"}, {"t": 90, "n": "גת רימון", "i": "358"}, {"t": 15, "n": "להבות הבשן", "i": "674"}, {"t": 60, "n": "חצב", "i": "465"}, {"t": 30, "n": "פלך", "i": "1058"}, {"t": 45, "n": "גילת", "i": "324"}, {"t": 30, "n": "אלמגור", "i": "120"}, {"t": 90, "n": "שדה ורבורג", "i": "1204"}, {"t": 45, "n": "זרחיה", "i": "423"}, {"t": 90, "n": "בית יהושע", "i": "202"}, {"t": 60, "n": "כפר קיש", "i": "646"}, {"t": 60, "n": "רכסים", "i": "1165"}, {"t": 0, "n": "ברעם", "i": "262"}, {"t": 60, "n": "מעון צופיה", "i": "773"}, {"t": 90, "n": "המרכז האקדמי רופין", "i": "395"}, {"t": 60, "n": "גני חוגה", "i": "1414"}, {"t": 60, "n": "עילבון", "i": "978"}, {"t": 90, "n": "ערערה", "i": "1042"}, {"t": 90, "n": "קיסריה", "i": "1109"}, {"t": 90, "n": "יסודות", "i": "524"}, {"t": 15, "n": "מטווח ניר עם", "i": "1348"}, {"t": 90, "n": "עמינדב", "i": "1024"}, {"t": 30, "n": "ניר משה", "i": "907"}, {"t": 90, "n": "צפריה", "i": "1090"}, {"t": 90, "n": "אזור תעשייה נשר - רמלה", "i": "61"}, {"t": 45, "n": "דניאל", "i": "1382"}, {"t": 60, "n": "מצפה", "i": "798"}, {"t": 15, "n": "כפר מימון ותושיה", "i": "627"}, {"t": 90, "n": "יעף", "i": "527"}, {"t": 45, "n": "שתולים", "i": "1270"}, {"t": 60, "n": "חזון", "i": "449"}, {"t": 30, "n": "בת הדר", "i": "267"}, {"t": 90, "n": "ברקת", "i": "265"}, {"t": 90, "n": "ישעי", "i": "549"}, {"t": 60, "n": "ביר אלמכסור", "i": "172"}, {"t": 90, "n": "בת ים", "i": "266"}, {"t": 30, "n": "מלון אחוזת ירדן", "i": "2020"}, {"t": 60, "n": "גבעת אבני", "i": "290"}, {"t": 60, "n": "בית גמליאל", "i": "183"}, {"t": 90, "n": "כפר יעבץ", "i": "623"}, {"t": 90, "n": "תקוע", "i": "1304"}, {"t": 30, "n": "מחניים", "i": "736"}, {"t": 90, "n": "גאולי תימן", "i": "279"}, {"t": 30, "n": "אזור תעשייה נ.ע.מ", "i": "1385"}, {"t": 90, "n": "נתיב הל''ה", "i": "931"}, {"t": 90, "n": "אום אל קוטוף", "i": "28"}, {"t": 30, "n": "עמיעד", "i": "1025"}, {"t": 90, "n": "עין אל סהלה", "i": "981"}, {"t": 90, "n": "חדרה - מזרח", "i": "6010"}, {"t": 90, "n": "חדרה - מערב", "i": "6011"}, {"t": 90, "n": "חדרה - מרכז", "i": "6012"}, {"t": 90, "n": "חדרה - נווה חיים", "i": "6013"}, {"t": 90, "n": "לוד", "i": "677"}, {"t": 60, "n": "ריינה", "i": "1162"}, {"t": 0, "n": "שניר", "i": "1250"}, {"t": 90, "n": "מתחם צומת שוקת", "i": "836"}, {"t": 90, "n": "אבנת", "i": "18"}, {"t": 90, "n": "בני ציון", "i": "245"}, {"t": 15, "n": "זמרת, שובה", "i": "1311"}, {"t": 90, "n": "עטרת", "i": "975"}, {"t": 30, "n": "טל - אל", "i": "487"}, {"t": 90, "n": "שדי חמד", "i": "1216"}, {"t": 90, "n": "פלמחים", "i": "1059"}, {"t": 90, "n": "כפר ויתקין", "i": "605"}, {"t": 60, "n": "אפק", "i": "136"}, {"t": 90, "n": "קריית ענבים", "i": "1127"}, {"t": 30, "n": "שפר", "i": "1261"}, {"t": 60, "n": "שכניה", "i": "1240"}, {"t": 90, "n": "ניר צבי", "i": "912"}, {"t": 60, "n": "בית אלעזרי", "i": "177"}, {"t": 45, "n": "אזור תעשייה תימורים", "i": "77"}, {"t": 90, "n": "בני דרור", "i": "240"}, {"t": 90, "n": "סתריה", "i": "954"}, {"t": 60, "n": "הרדוף", "i": "406"}, {"t": 90, "n": "אור עקיבא", "i": "34"}, {"t": 90, "n": "נאות סמדר", "i": "843"}, {"t": 45, "n": "שובל", "i": "1224"}, {"t": 30, "n": "נחף", "i": "885"}, {"t": 90, "n": "קריית נטפים", "i": "1126"}, {"t": 60, "n": "כפר חסידים", "i": "614"}, {"t": 30, "n": "אילות", "i": "91"}, {"t": 60, "n": "רשפים", "i": "1188"}, {"t": 60, "n": "טורעאן", "i": "480"}, {"t": 90, "n": "מבשרת ציון", "i": "699"}, {"t": 15, "n": "עין גב", "i": "984"}, {"t": 30, "n": "מכמנים", "i": "403"}, {"t": 90, "n": "נופי נחמיה", "i": "871"}, {"t": 90, "n": "עלי", "i": "1019"}, {"t": 90, "n": "בית ברל", "i": "180"}, {"t": 60, "n": "אזור תעשייה קדמת גליל", "i": "69"}, {"t": 30, "n": "טובא זנגריה", "i": "479"}, {"t": 90, "n": "רחלים", "i": "1158"}, {"t": 90, "n": "גבעת כ''ח", "i": "303"}, {"t": 90, "n": "בית עובד", "i": "218"}, {"t": 90, "n": "מזור", "i": "731"}, {"t": 90, "n": "יד רמב''ם", "i": "507"}, {"t": 60, "n": "שורשים", "i": "1230"}, {"t": 90, "n": "ברטעה", "i": "260"}, {"t": 45, "n": "שפיר", "i": "1260"}, {"t": 90, "n": "בית חזון", "i": "196"}, {"t": 30, "n": "גיתה", "i": "327"}, {"t": 45, "n": "קוממיות", "i": "1105"}, {"t": 90, "n": "תעשיון צריפין", "i": "1300"}, {"t": 90, "n": "בית עוזיאל", "i": "219"}, {"t": 30, "n": "אשבול", "i": "143"}, {"t": 90, "n": "שקד", "i": "1263"}, {"t": 90, "n": "מייסר", "i": "741"}, {"t": 30, "n": "תאשור", "i": "1271"}, {"t": 0, "n": "עין קנייא", "i": "1008"}, {"t": 60, "n": "אלומות", "i": "103"}, {"t": 90, "n": "בן שמן", "i": "236"}, {"t": 45, "n": "קריית חינוך מרחבים", "i": "1131"}, {"t": 0, "n": "עבדון", "i": "955"}, {"t": 90, "n": "חירן", "i": "1373"}, {"t": 90, "n": "דימונה", "i": "369"}, {"t": 60, "n": "מעלה צביה", "i": "788"}, {"t": 90, "n": "שער הגיא", "i": "1446"}, {"t": 90, "n": "אזור תעשייה רותם", "i": "72"}, {"t": 90, "n": "אזור תעשייה ברוש", "i": "48"}, {"t": 15, "n": "תלמי אליהו", "i": "1289"}, {"t": 90, "n": "עין חצבה", "i": "998"}, {"t": 30, "n": "תובל", "i": "1273"}, {"t": 45, "n": "אשדוד - א,ב,ד,ה", "i": "6000"}, {"t": 45, "n": "אשדוד - ג,ו,ז", "i": "6001"}, {"t": 45, "n": "אשדוד - ח,ט,י,יג,יד,טז", "i": "6002"}, {"t": 45, "n": "אשדוד -יא,יב,טו,יז,מרינה,סיטי", "i": "6003"}, {"t": 0, "n": "בן עמי", "i": "235"}, {"t": 60, "n": "מישר", "i": "746"}, {"t": 15, "n": "חוות יזרעם", "i": "1303"}, {"t": 30, "n": "מרכז אזורי מרום גליל", "i": "1354"}, {"t": 60, "n": "פארק תעשייה ראם", "i": "1048"}, {"t": 90, "n": "רמות מנשה", "i": "1170"}, {"t": 60, "n": "כפר אביב", "i": "579"}, {"t": 60, "n": "צפרירים", "i": "1091"}, {"t": 90, "n": "פסגות", "i": "1062"}, {"t": 60, "n": "דגניה א", "i": "362"}, {"t": 60, "n": "רומאנה", "i": "1152"}, {"t": 15, "n": "פרי גן", "i": "1070"}, {"t": 60, "n": "עתלית", "i": "1044"}, {"t": 60, "n": "שפרעם", "i": "1262"}, {"t": 90, "n": "צומת בנימינה", "i": "1441"}, {"t": 90, "n": "קידר", "i": "1101"}, {"t": 90, "n": "מכורה", "i": "749"}, {"t": 30, "n": "שבי ציון", "i": "1194"}, {"t": 90, "n": "אזור תעשייה עמק חפר", "i": "64"}, {"t": 60, "n": "כפר ביאליק", "i": "584"}, {"t": 60, "n": "כפר החורש", "i": "597"}, {"t": 60, "n": "ח'וואלד", "i": "425"}, {"t": 90, "n": "כפר יונה", "i": "620"}, {"t": 90, "n": "אזור תעשייה טירה", "i": "53"}, {"t": 90, "n": "צור נתן", "i": "1084"}, {"t": 30, "n": "פעמי תש''ז", "i": "1064"}, {"t": 15, "n": "יכיני", "i": "519"}, {"t": 90, "n": "נוקדים", "i": "876"}, {"t": 0, "n": "צבעון", "i": "1074"}, {"t": 90, "n": "גבעת עוז", "i": "306"}, {"t": 90, "n": "אבו גוש", "i": "1"}, {"t": 90, "n": "כוכב השחר", "i": "557"}, {"t": 30, "n": "אליפלט", "i": "116"}, {"t": 0, "n": "רמת מגשימים", "i": "1180"}, {"t": 90, "n": "אלון מורה", "i": "106"}, {"t": 90, "n": "אירוס", "i": "94"}, {"t": 60, "n": "אבטליון", "i": "5"}, {"t": 60, "n": "תירוש", "i": "1278"}, {"t": 45, "n": "פדויים", "i": "1050"}, {"t": 90, "n": "קטורה", "i": "1107"}, {"t": 90, "n": "ניר אליהו", "i": "900"}, {"t": 60, "n": "עפולה", "i": "1032"}, {"t": 30, "n": "נתיב השיירה", "i": "933"}, {"t": 60, "n": "כפר כנא", "i": "625"}, {"t": 90, "n": "גן שלמה", "i": "340"}, {"t": 90, "n": "יקנעם המושבה והזורע", "i": "1313"}, {"t": 60, "n": "שדה יעקב", "i": "1206"}, {"t": 15, "n": "בני יהודה וגבעת יואב", "i": "241"}, {"t": 90, "n": "פצאל", "i": "1065"}, {"t": 60, "n": "אזור תעשייה מבואות הגלבוע", "i": "A86864022FD67E9CF182AEED02482635"}, {"t": 90, "n": "חולון", "i": "439"}, {"t": 0, "n": "קיבוץ דן", "i": "377"}, {"t": 60, "n": "הררית יחד", "i": "407"}, {"t": 30, "n": "אזור תעשייה צפוני אשקלון", "i": "68"}, {"t": 90, "n": "סינמה סיטי גלילות", "i": "1379"}, {"t": 60, "n": "קדרים", "i": "1103"}, {"t": 60, "n": "עין חרוד", "i": "1333"}, {"t": 30, "n": "קדיתא", "i": "1098"}, {"t": 15, "n": "תקומה", "i": "1349"}, {"t": 30, "n": "תלמים", "i": "1295"}, {"t": 90, "n": "משואה", "i": "821"}, {"t": 0, "n": "אורטל", "i": "37"}, {"t": 0, "n": "בוקעתא", "i": "167"}, {"t": 30, "n": "צורית גילון", "i": "1320"}, {"t": 90, "n": "גבעת השלושה", "i": "293"}, {"t": 90, "n": "רחובות", "i": "1157"}, {"t": 15, "n": "פקיעין", "i": "1066"}, {"t": 90, "n": "תל שבע", "i": "1286"}, {"t": 90, "n": "בית חורון", "i": "195"}, {"t": 60, "n": "סלמה", "i": "944"}, {"t": 90, "n": "כפר סירקין", "i": "640"}, {"t": 60, "n": "כפר הנגיד", "i": "599"}, {"t": 90, "n": "מועאוויה", "i": "722"}, {"t": 90, "n": "הר הנגב", "i": "1376"}, {"t": 90, "n": "בקוע", "i": "253"}, {"t": 60, "n": "חצרים", "i": "469"}, {"t": 90, "n": "גזר", "i": "320"}, {"t": 90, "n": "בר גיורא", "i": "255"}, {"t": 60, "n": "אזור תעשייה קריית ביאליק", "i": "1406"}, {"t": 60, "n": "קריית ביאליק", "i": "1119"}, {"t": 15, "n": "מעלה גמלא", "i": "781"}, {"t": 90, "n": "עולש", "i": "965"}, {"t": 60, "n": "ציפורי", "i": "1088"}, {"t": 60, "n": "מולדת", "i": "721"}, {"t": 60, "n": "יד בנימין", "i": "502"}, {"t": 90, "n": "ירחיב", "i": "543"}, {"t": 0, "n": "איזור תעשייה מילואות צפון", "i": "1562"}, {"t": 60, "n": "מרכז מיר''ב", "i": "815"}, {"t": 30, "n": "קצרין", "i": "1116"}, {"t": 30, "n": "כורזים ורד הגליל", "i": "561"}, {"t": 15, "n": "צוחר, אוהד", "i": "1076"}, {"t": 90, "n": "הוד השרון", "i": "385"}, {"t": 15, "n": "עין השלושה", "i": "994"}, {"t": 30, "n": "ניצנים", "i": "899"}, {"t": 90, "n": "כפר הנוקדים", "i": "1430"}, {"t": 60, "n": "בלפוריה", "i": "233"}, {"t": 60, "n": "ואדי אל חמאם", "i": "408"}, {"t": 60, "n": "צומת האלה", "i": "1443"}, {"t": 90, "n": "דולב", "i": "365"}, {"t": 45, "n": "אשדוד - כל האזורים", "i": "4EF9DBE1EADDD14FAE26D0C71715ED70"}, {"t": 60, "n": "באר שבע - כל האזורים", "i": "22BB794E3717207E022D37B3350E7DF9"}, {"t": 90, "n": "הרצליה - כל האזורים", "i": "9AF7CB83A9FF8C70ACFB8884346F41D1"}, {"t": 90, "n": "חדרה כל - האזורים", "i": "426F12F90BDAE55B6AE0A7C0F34F8A60"}, {"t": 60, "n": "חיפה - כל האזורים", "i": "8A73B087F0C68399B7DB73D694056ADB"}, {"t": 90, "n": "ירושלים - כל האזורים", "i": "3774C787EB3F9D984C25AB978DE753C0"}, {"t": 90, "n": "נתניה - כל האזורים", "i": "66C0EDF2ED3811C5B107548A6C414971"}, {"t": 90, "n": "בית סוהר מגידו", "i": "213"}, {"t": 90, "n": "ראשון לציון - כל האזורים", "i": "0B0025E3510C4E14DAC82BBF20FA9436"}, {"t": 90, "n": "רמת גן - כל האזורים", "i": "6F91F6ED69CA5FF7E1ED26090BD6FEF7"}, {"t": 90, "n": "תל אביב - כל האזורים", "i": "2A05FC394B6E9B8A29A77EB62C105291"}, {"t": 30, "n": "אשקלון - כל האזורים", "i": "CD8280C0897944DB7635BD196667A37D"}, {"t": 90, "n": "חגור", "i": "429"}, {"t": 90, "n": "מודיעין - ישפרו סנטר", "i": "717"}, {"t": 30, "n": "כסרא סמיע", "i": "567"}, {"t": 30, "n": "מעגלים, גבעולים, מלילות", "i": "768"}, {"t": 30, "n": "צפת - כל האזורים", "i": "338C321A340340DD3E702340D479FF4C"}, {"t": 60, "n": "נגוהות", "i": "848"}, {"t": 90, "n": "גרופית", "i": "353"}, {"t": 90, "n": "רביבים", "i": "1144"}, {"t": 45, "n": "באר טוביה", "i": "159"}, {"t": 60, "n": "ישובי יעל", "i": "1325"}, {"t": 30, "n": "קלחים", "i": "1110"}, {"t": 90, "n": "רמת השרון", "i": "1177"}, {"t": 30, "n": "אזור תעשייה חצור הגלילית", "i": "52"}, {"t": 60, "n": "כרמי קטיף", "i": "664"}, {"t": 90, "n": "עינת", "i": "1014"}, {"t": 90, "n": "מלונות ים המלח מרכז", "i": "751"}, {"t": 30, "n": "בענה", "i": "250"}, {"t": 30, "n": "הר חלוץ", "i": "398"}, {"t": 90, "n": "אבו תלול", "i": "2"}, {"t": 60, "n": "עין דור", "i": "986"}, {"t": 60, "n": "נאעורה", "i": "1438"}, {"t": 30, "n": "תלמי יפה", "i": "1294"}, {"t": 60, "n": "טירת כרמל", "i": "485"}, {"t": 90, "n": "נצר חזני", "i": "924"}, {"t": 45, "n": "להבים", "i": "676"}, {"t": 30, "n": "ניר ישראל", "i": "906"}, {"t": 90, "n": "כפר קאסם", "i": "645"}, {"t": 45, "n": "בטחה", "i": "170"}, {"t": 15, "n": "נחל עוז", "i": "880"}, {"t": 90, "n": "רועי", "i": "1154"}, {"t": 90, "n": "נתניה - מזרח", "i": "6023"}, {"t": 90, "n": "נתניה - מערב", "i": "6024"}, {"t": 60, "n": "פוריה נווה עובד", "i": "1053"}, {"t": 90, "n": "מבוא חורון", "i": "692"}, {"t": 90, "n": "בת חפר", "i": "269"}, {"t": 30, "n": "האון", "i": "381"}, {"t": 90, "n": "כוכב יעקב", "i": "559"}, {"t": 60, "n": "רמת ישי", "i": "1179"}, {"t": 60, "n": "עראבה", "i": "1036"}, {"t": 60, "n": "כנות", "i": "573"}, {"t": 15, "n": "מצוק עורבים", "i": "1435"}, {"t": 60, "n": "יעד", "i": "526"}, {"t": 90, "n": "בת עין", "i": "270"}, {"t": 60, "n": "כפר תבור", "i": "653"}, {"t": 90, "n": "גן שמואל", "i": "341"}, {"t": 0, "n": "שאר ישוב", "i": "1191"}, {"t": 60, "n": "מגן שאול", "i": "711"}, {"t": 30, "n": "קצרין - אזור תעשייה", "i": "1117"}, {"t": 90, "n": "ניצני עוז", "i": "898"}, {"t": 90, "n": "כפר סבא", "i": "638"}, {"t": 90, "n": "מבוא דותן", "i": "691"}, {"t": 45, "n": "לכיש", "i": "684"}, {"t": 15, "n": "רמת טראמפ", "i": "1449"}, {"t": 60, "n": "אתר ההנצחה גולני", "i": "155"}, {"t": 30, "n": "אזור תעשייה כרמיאל", "i": "56"}, {"t": 90, "n": "חצבה", "i": "466"}, {"t": 90, "n": "בית אריה", "i": "179"}, {"t": 60, "n": "פוריה עילית", "i": "1054"}, {"t": 60, "n": "כפר יהושע", "i": "619"}, {"t": 0, "n": "נאות מרדכי", "i": "842"}, {"t": 15, "n": "חולית", "i": "440"}, {"t": 30, "n": "ראמה", "i": "1135"}, {"t": 90, "n": "אזור תעשייה שער בנימין", "i": "75"}, {"t": 60, "n": "אזור תעשייה שער נעמן", "i": "76"}, {"t": 90, "n": "מיתר", "i": "747"}, {"t": 90, "n": "רמות השבים", "i": "1168"}, {"t": 45, "n": "אחווה", "i": "79"}, {"t": 90, "n": "חרב לאת", "i": "470"}, {"t": 0, "n": "נמרוד", "i": "915"}, {"t": 45, "n": "תלמי יחיאל", "i": "1293"}, {"t": 90, "n": "אלפי מנשה", "i": "124"}, {"t": 90, "n": "משמר השרון", "i": "830"}, {"t": 0, "n": "עלמה", "i": "1021"}, {"t": 60, "n": "עומר", "i": "966"}, {"t": 90, "n": "שעלבים", "i": "1253"}, {"t": 90, "n": "מעגן מיכאל", "i": "770"}, {"t": 15, "n": "תלמי יוסף", "i": "1292"}, {"t": 30, "n": "מסדה", "i": "761"}, {"t": 0, "n": "קריית שמונה", "i": "1132"}, {"t": 90, "n": "פדואל", "i": "1049"}, {"t": 60, "n": "שבלי", "i": "1196"}, {"t": 90, "n": "בורגתה", "i": "168"}, {"t": 90, "n": "רמת גן - מזרח", "i": "6027"}, {"t": 90, "n": "רמת גן - מערב", "i": "6028"}, {"t": 90, "n": "גבעת אסף", "i": "1368"}, {"t": 60, "n": "בסמת טבעון", "i": "249"}, {"t": 15, "n": "סעד", "i": "950"}, {"t": 90, "n": "גיבתון", "i": "322"}, {"t": 60, "n": "מרכז אזורי משגב", "i": "813"}, {"t": 90, "n": "שמעה", "i": "1247"}, {"t": 60, "n": "כעביה טבאש", "i": "578"}, {"t": 90, "n": "רטורנו - גבעת שמש", "i": "1159"}, {"t": 60, "n": "חוות עדן", "i": "434"}, {"t": 90, "n": "רמלה", "i": "1172"}, {"t": 15, "n": "שוקדה", "i": "1228"}, {"t": 90, "n": "עין נקובא", "i": "1005"}, {"t": 45, "n": "גבעות בר", "i": "288"}, {"t": 0, "n": "אדמית", "i": "21"}, {"t": 60, "n": "עגור", "i": "959"}, {"t": 0, "n": "שלומי", "i": "1243"}, {"t": 30, "n": "מג'דל כרום", "i": "700"}, {"t": 60, "n": "מתחם סקי גלבוע", "i": "2191"}, {"t": 30, "n": "שלומית", "i": "1244"}, {"t": 90, "n": "מבוא מודיעים", "i": "694"}, {"t": 60, "n": "רמת יוחנן", "i": "1178"}, {"t": 90, "n": "שדות ים", "i": "1214"}, {"t": 30, "n": "אורים", "i": "38"}, {"t": 30, "n": "אמירים", "i": "128"}, {"t": 30, "n": "שייח' דנון", "i": "1237"}, {"t": 90, "n": "אזור תעשייה שער בנימין", "i": "6A8D706EE234187FE07CCD4A6B5DB7FE"}, {"t": 0, "n": "לימן", "i": "683"}, {"t": 90, "n": "נצר סרני", "i": "925"}, {"t": 90, "n": "לפיד", "i": "685"}, {"t": 60, "n": "קריית ים", "i": "1122"}, {"t": 0, "n": "חוף בצת", "i": "1418"}, {"t": 90, "n": "נס ציונה", "i": "918"}, {"t": 60, "n": "טבחה", "i": "1428"}, {"t": 60, "n": "עין חוד", "i": "997"}, {"t": 90, "n": "בנימינה", "i": "248"}, {"t": 60, "n": "הזורעים", "i": "389"}, {"t": 90, "n": "הר עמשא", "i": "404"}, {"t": 90, "n": "באקה אל גרבייה", "i": "156"}, {"t": 60, "n": "מרכז חבר", "i": "1326"}, {"t": 90, "n": "אבן ספיר", "i": "14"}, {"t": 30, "n": "בני נצרים", "i": "242"}, {"t": 0, "n": "מצובה", "i": "795"}, {"t": 60, "n": "בית צבי", "i": "223"}, {"t": 90, "n": "מצוקי דרגות", "i": "796"}, {"t": 30, "n": "עוזה", "i": "963"}, {"t": 60, "n": "אליאב", "i": "113"}, {"t": 0, "n": "ריחאנייה", "i": "1160"}, {"t": 90, "n": "הר אדר", "i": "399"}, {"t": 60, "n": "משהד", "i": "820"}, {"t": 60, "n": "שדמה", "i": "1218"}, {"t": 60, "n": "אזור תעשייה בר-לב", "i": "46"}, {"t": 90, "n": "כפר דניאל", "i": "595"}, {"t": 60, "n": "אושה", "i": "41"}, {"t": 0, "n": "הגושרים", "i": "383"}, {"t": 90, "n": "מצליח", "i": "797"}, {"t": 15, "n": "חוף גופרה", "i": "1420"}, {"t": 90, "n": "בית נקופה", "i": "211"}, {"t": 90, "n": "אל עריאן", "i": "100"}, {"t": 90, "n": "בית דגן", "i": "184"}, {"t": 90, "n": "אליפז ומכרות תמנע", "i": "115"}, {"t": 90, "n": "ביתר עילית", "i": "232"}, {"t": 60, "n": "בית לחם הגלילית", "i": "207"}, {"t": 30, "n": "חולתה", "i": "441"}, {"t": 90, "n": "רמת השופט", "i": "1176"}, {"t": 60, "n": "כפר גלים", "i": "591"}, {"t": 90, "n": "חניון הנתיב מהיר", "i": "1427"}, {"t": 60, "n": "בת שלמה", "i": "271"}, {"t": 90, "n": "שדה יצחק", "i": "1207"}, {"t": 90, "n": "קיבוץ מגידו", "i": "708"}, {"t": 0, "n": "תל חי", "i": "1279"}, {"t": 90, "n": "חורשים", "i": "448"}, {"t": 15, "n": "חמת גדר", "i": "459"}, {"t": 15, "n": "צוחר, אוהד", "i": "1371"}, {"t": 45, "n": "חוף ניצנים", "i": "1424"}, {"t": 90, "n": "נס הרים", "i": "916"}, {"t": 60, "n": "אל-ח'וואלד מערב", "i": "98"}, {"t": 60, "n": "בית יוסף", "i": "203"}, {"t": 15, "n": "חוות שיקמים", "i": "437"}, {"t": 0, "n": "שתולה", "i": "1269"}, {"t": 15, "n": "שדי אברהם", "i": "1198"}, {"t": 90, "n": "אזור תעשייה דימונה", "i": "49"}, {"t": 90, "n": "עזוז", "i": "970"}, {"t": 60, "n": "יגור", "i": "500"}, {"t": 30, "n": "בית העלמין החדש עכו", "i": "1412"}, {"t": 30, "n": "עכו", "i": "1016"}, {"t": 30, "n": "עכו - אזור תעשייה", "i": "1017"}, {"t": 90, "n": "כפר נטר", "i": "636"}, {"t": 90, "n": "צרעה", "i": "1094"}, {"t": 90, "n": "ביתן אהרן", "i": "231"}, {"t": 60, "n": "פוריידיס", "i": "1055"}, {"t": 90, "n": "מעברות", "i": "767"}, {"t": 60, "n": "אלוני אבא", "i": "108"}, {"t": 30, "n": "עמקה", "i": "1029"}, {"t": 60, "n": "הושעיה", "i": "388"}, {"t": 45, "n": "עזר", "i": "971"}, {"t": 60, "n": "גינוסר", "i": "325"}, {"t": 15, "n": "חוסן", "i": "442"}, {"t": 90, "n": "קידה", "i": "1108"}, {"t": 0, "n": "מתת", "i": "838"}, {"t": 90, "n": "בתי מלון ים המלח", "i": "272"}, {"t": 0, "n": "רמות נפתלי", "i": "1171"}, {"t": 90, "n": "כפר מונש", "i": "626"}, {"t": 45, "n": "אשל הנשיא", "i": "150"}, {"t": 60, "n": "אעבלין", "i": "133"}, {"t": 90, "n": "כפר הס", "i": "602"}, {"t": 45, "n": "ניר בנים", "i": "901"}, {"t": 60, "n": "נהלל", "i": "850"}, {"t": 45, "n": "גן יבנה", "i": "337"}, {"t": 90, "n": "חיבת ציון", "i": "451"}, {"t": 45, "n": "עזריקם", "i": "974"}, {"t": 90, "n": "אחיטוב", "i": "84"}, {"t": 30, "n": "עוצם", "i": "969"}, {"t": 90, "n": "מגרון", "i": "712"}, {"t": 90, "n": "יקיר", "i": "537"}, {"t": 90, "n": "שדה בוקר", "i": "1202"}, {"t": 60, "n": "כרם ביבנה", "i": "658"}, {"t": 90, "n": "כפר טרומן", "i": "617"}, {"t": 90, "n": "שערי תקווה", "i": "1258"}, {"t": 30, "n": "כפר סילבר", "i": "639"}, {"t": 15, "n": "מבוא חמה", "i": "693"}, {"t": 60, "n": "מגדל העמק", "i": "704"}, {"t": 0, "n": "קשת", "i": "1134"}, {"t": 60, "n": "טייבה בגלבוע", "i": "482"}, {"t": 90, "n": "תומר", "i": "1274"}, {"t": 60, "n": "תל עדשים", "i": "1283"}, {"t": 60, "n": "נחשולים", "i": "886"}, {"t": 60, "n": "אחוזת ברק", "i": "81"}, {"t": 90, "n": "יטבתה", "i": "517"}, {"t": 90, "n": "חרשה", "i": "475"}, {"t": 90, "n": "היישוב היהודי חברון", "i": "427"}, {"t": 60, "n": "נבי שועייב", "i": "1439"}, {"t": 90, "n": "עין ורד", "i": "995"}, {"t": 45, "n": "מנוחה", "i": "753"}, {"t": 60, "n": "ואדי אל נעם דרום", "i": "409"}, {"t": 90, "n": "עיר אובות", "i": "1015"}, {"t": 60, "n": "בית זרע", "i": "193"}, {"t": 90, "n": "צוקים", "i": "1080"}, {"t": 60, "n": "יבנאל", "i": "498"}, {"t": 60, "n": "חיפה - כרמל, הדר ועיר תחתית", "i": "6014"}, {"t": 60, "n": "חיפה - מערב", "i": "6015"}, {"t": 60, "n": "חיפה - מפרץ", "i": "6016"}, {"t": 60, "n": "חיפה - נווה שאנן ורמות כרמל", "i": "6017"}, {"t": 60, "n": "חיפה - קריית חיים ושמואל", "i": "6034"}, {"t": 90, "n": "גן שורק", "i": "339"}, {"t": 60, "n": "עוזייר", "i": "964"}, {"t": 90, "n": "כפר אדומים", "i": "580"}, {"t": 60, "n": "כפר נהר הירדן", "i": "634"}, {"t": 90, "n": "בית סוהר נפחא", "i": "214"}, {"t": 60, "n": "מירב", "i": "744"}, {"t": 15, "n": "נתיב העשרה", "i": "932"}, {"t": 90, "n": "משכיות", "i": "823"}, {"t": 90, "n": "ג'לג'וליה", "i": "275"}, {"t": 90, "n": "קריית עקרון", "i": "1128"}, {"t": 60, "n": "בית אלפא וחפציבה", "i": "178"}, {"t": 0, "n": "בית הלל", "i": "187"}, {"t": 60, "n": "עין מאהל", "i": "1004"}, {"t": 90, "n": "מיצד", "i": "742"}, {"t": 30, "n": "אבו סנאן", "i": "3"}, {"t": 90, "n": "מעש", "i": "792"}, {"t": 60, "n": "סנסנה", "i": "949"}, {"t": 60, "n": "ישובי אומן", "i": "546"}, {"t": 60, "n": "היוגב", "i": "391"}, {"t": 90, "n": "זמר", "i": "418"}, {"t": 90, "n": "משמר דוד", "i": "825"}, {"t": 60, "n": "שדמות דבורה", "i": "1219"}, {"t": 90, "n": "תלמי אלעזר", "i": "1290"}, {"t": 60, "n": "איבטין", "i": "87"}, {"t": 60, "n": "קדש ברנע", "i": "1104"}, {"t": 90, "n": "יד השמונה", "i": "503"}, {"t": 90, "n": "תל מונד", "i": "1282"}, {"t": 30, "n": "חלץ", "i": "454"}, {"t": 0, "n": "חוות אירוח גורן", "i": "1416"}, {"t": 0, "n": "מעונה", "i": "774"}, {"t": 90, "n": "תל יצחק", "i": "1281"}, {"t": 90, "n": "אום אל פחם", "i": "27"}, {"t": 60, "n": "סולם", "i": "940"}, {"t": 30, "n": "כפר נחום", "i": "1431"}, {"t": 15, "n": "כרמיה", "i": "666"}, {"t": 90, "n": "מבוא ביתר", "i": "690"}, {"t": 90, "n": "קדימה צורן", "i": "1097"}, {"t": 30, "n": "דיר אל-אסד", "i": "370"}, {"t": 0, "n": "פקיעין החדשה", "i": "1337"}, {"t": 30, "n": "ג'דידה מכר", "i": "273"}, {"t": 0, "n": "בצת", "i": "252"}, {"t": 30, "n": "עמוקה", "i": "1023"}, {"t": 15, "n": "סופה", "i": "942"}, {"t": 60, "n": "עין איילה", "i": "980"}, {"t": 90, "n": "גבעת שפירא", "i": "308"}, {"t": 90, "n": "נופי פרת", "i": "872"}, {"t": 30, "n": "אילת", "i": "93"}, {"t": 45, "n": "ניר גלים", "i": "902"}, {"t": 90, "n": "מוצא עילית", "i": "727"}, {"t": 30, "n": "מזרעה", "i": "734"}, {"t": 60, "n": "דלית אל כרמל", "i": "374"}, {"t": 90, "n": "בית עריף", "i": "222"}, {"t": 60, "n": "נטע", "i": "891"}, {"t": 30, "n": "כפר הנשיא", "i": "601"}, {"t": 60, "n": "כינרת קבוצה", "i": "565"}, {"t": 90, "n": "חמרה", "i": "458"}, {"t": 15, "n": "שדה ניצן", "i": "1211"}, {"t": 90, "n": "קריית ארבע", "i": "1129"}, {"t": 60, "n": "פוריה כפר עבודה", "i": "1052"}, {"t": 90, "n": "שיטים", "i": "1236"}, {"t": 0, "n": "אביבים", "i": "7"}, {"t": 45, "n": "דביר", "i": "360"}, {"t": 90, "n": "צלפון", "i": "1089"}, {"t": 60, "n": "כפר הנוער ימין אורד", "i": "600"}, {"t": 30, "n": "שחר", "i": "1233"}, {"t": 30, "n": "כפר יאסיף", "i": "622"}, {"t": 90, "n": "מיני ישראל - נחשון", "i": "1956"}, {"t": 90, "n": "יגל", "i": "501"}, {"t": 90, "n": "גני הדר", "i": "344"}, {"t": 90, "n": "גיזו", "i": "323"}, {"t": 15, "n": "מלון פרא", "i": "2181"}, {"t": 90, "n": "קליה", "i": "1111"}, {"t": 45, "n": "אלומה", "i": "102"}, {"t": 60, "n": "תל תאומים", "i": "1287"}, {"t": 90, "n": "חוף קליה", "i": "1426"}, {"t": 90, "n": "אזור תעשייה בראון", "i": "47"}, {"t": 90, "n": "אבו נוור", "i": "1400"}, {"t": 60, "n": "אילניה", "i": "92"}, {"t": 90, "n": "גבע בנימין", "i": "285"}, {"t": 90, "n": "אביחיל", "i": "9"}, {"t": 90, "n": "הראל", "i": "405"}, {"t": 90, "n": "בית יצחק - שער חפר", "i": "205"}, {"t": 90, "n": "אזור תעשייה הר טוב - צרעה", "i": "51"}, {"t": 90, "n": "גני עם", "i": "347"}, {"t": 90, "n": "אדורה", "i": "20"}, {"t": 60, "n": "אפיקים", "i": "135"}, {"t": 90, "n": "חורה", "i": "446"}, {"t": 90, "n": "מטע", "i": "739"}, {"t": 15, "n": "שדרות, איבים", "i": "1307"}, {"t": 60, "n": "רמת דוד", "i": "1173"}, {"t": 60, "n": "אמציה", "i": "131"}, {"t": 0, "n": "כל הארץ", "i": "9999"}, {"t": 60, "n": "כפר ברוך", "i": "589"}, {"t": 60, "n": "אזור תעשייה רבדים", "i": "1407"}, {"t": 90, "n": "אשתאול", "i": "154"}, {"t": 60, "n": "אלונים", "i": "111"}, {"t": 45, "n": "רווחה", "i": "1149"}, {"t": 60, "n": "נוה איתן", "i": "858"}, {"t": 90, "n": "מענית", "i": "791"}, {"t": 90, "n": "שבות רחל", "i": "1192"}, {"t": 90, "n": "הרצליה - מערב", "i": "6009"}, {"t": 90, "n": "הרצליה - מרכז וגליל ים", "i": "6008"}, {"t": 30, "n": "מגדל תפן", "i": "706"}, {"t": 90, "n": "כרמי יוסף", "i": "662"}, {"t": 90, "n": "מסילת ציון", "i": "763"}, {"t": 90, "n": "גבעות עדן", "i": "289"}, {"t": 90, "n": "פתחיה", "i": "1072"}, {"t": 60, "n": "כפר רופין", "i": "648"}, {"t": 90, "n": "נטף", "i": "893"}, {"t": 90, "n": "עלי זהב", "i": "1020"}, {"t": 90, "n": "מצפה רמון", "i": "803"}, {"t": 60, "n": "בועיינה-נוג'ידאת", "i": "166"}, {"t": 90, "n": "מעלה אפרים", "i": "779"}, {"t": 30, "n": "צורית גילון", "i": "1086"}, {"t": 90, "n": "כפר עציון", "i": "643"}, {"t": 90, "n": "תלם", "i": "1288"}, {"t": 60, "n": "עין כרמל", "i": "1003"}, {"t": 60, "n": "כאוכב אבו אלהיג'א", "i": "553"}, {"t": 30, "n": "ג'וליס", "i": "274"}, {"t": 15, "n": "חוף גולן, צאלון", "i": "1419"}, {"t": 60, "n": "אשבל", "i": "144"}, {"t": 90, "n": "כסייפה", "i": "575"}, {"t": 60, "n": "מרכז חבר", "i": "1327"}, {"t": 60, "n": "כרמית", "i": "668"}, {"t": 90, "n": "מרחב עם", "i": "809"}, {"t": 90, "n": "תעוז", "i": "1298"}, {"t": 90, "n": "מדרשת בן גוריון", "i": "715"}, {"t": 90, "n": "חריש", "i": "473"}, {"t": 60, "n": "נוף הגליל", "i": "927"}, {"t": 45, "n": "כפר אחים", "i": "582"}, {"t": 0, "n": "כפר יובל", "i": "510"}, {"t": 60, "n": "לבנים", "i": "672"}, {"t": 60, "n": "כפר גמילה מלכישוע", "i": "594"}, {"t": 0, "n": "דלתון", "i": "375"}, {"t": 90, "n": "מעלה חבר", "i": "783"}, {"t": 30, "n": "נס עמים", "i": "917"}, {"t": 90, "n": "פנימיית עין כרם", "i": "1352"}, {"t": 30, "n": "ביריה", "i": "174"}, {"t": 90, "n": "גבעת שמואל", "i": "307"}, {"t": 60, "n": "ביצרון", "i": "171"}, {"t": 60, "n": "לוזית", "i": "678"}, {"t": 90, "n": "מצפה יריחו", "i": "801"}, {"t": 60, "n": "כרם מהר''ל", "i": "660"}, {"t": 90, "n": "גנות הדר", "i": "343"}, {"t": 90, "n": "עין גדי", "i": "985"}, {"t": 60, "n": "מנוף", "i": "754"}, {"t": 30, "n": "נווה", "i": "854"}, {"t": 90, "n": "מעלה עמוס", "i": "787"}, {"t": 90, "n": "עמיקם", "i": "1026"}, {"t": 0, "n": "אבירים", "i": "11"}, {"t": 90, "n": "עין ראפה", "i": "1009"}, {"t": 60, "n": "כפר חסידים", "i": "1343"}, {"t": 90, "n": "נתיב הגדוד", "i": "930"}, {"t": 30, "n": "אזור תעשייה צ.ח.ר", "i": "65"}, {"t": 90, "n": "נופים", "i": "873"}, {"t": 60, "n": "ניצנה", "i": "897"}, {"t": 90, "n": "סעווה", "i": "720"}, {"t": 90, "n": "גבעת חן", "i": "300"}, {"t": 30, "n": "ספסופה - כפר חושן", "i": "953"}, {"t": 60, "n": "רומת אל הייב", "i": "1153"}, {"t": 30, "n": "שומרת", "i": "1227"}, {"t": 30, "n": "איתן", "i": "96"}, {"t": 0, "n": "יונתן", "i": "513"}, {"t": 30, "n": "רגבה", "i": "1146"}, {"t": 30, "n": "לוחמי הגטאות", "i": "679"}, {"t": 60, "n": "לוטם וחמדון", "i": "680"}, {"t": 90, "n": "משמר השבעה", "i": "829"}, {"t": 60, "n": "תחנת רכבת קריית מלאכי - יואב", "i": "1448"}, {"t": 60, "n": "כלנית", "i": "571"}, {"t": 90, "n": "כפר נוער בן שמן", "i": "635"}, {"t": 45, "n": "גבעות גורל", "i": "1372"}, {"t": 0, "n": "דישון", "i": "372"}, {"t": 30, "n": "אזור תעשייה הדרומי אשקלון", "i": "50"}, {"t": 60, "n": "ישובי יעל", "i": "1324"}, {"t": 60, "n": "מורשת", "i": "730"}, {"t": 90, "n": "אזור תעשייה מבוא כרמל", "i": "57"}, {"t": 60, "n": "אזור תעשייה מבואות הגלבוע", "i": "58"}, {"t": 30, "n": "עין אל אסד", "i": "982"}, {"t": 90, "n": "כפר שמריהו", "i": "652"}, {"t": 90, "n": "פארק תעשיות מגדל עוז", "i": "1440"}, {"t": 15, "n": "אניעם", "i": "132"}, {"t": 30, "n": "בית העמק", "i": "188"}, {"t": 90, "n": "אזור תעשייה קיסריה", "i": "70"}, {"t": 30, "n": "גבולות", "i": "282"}, {"t": 60, "n": "גפן", "i": "352"}, {"t": 30, "n": "מבועים", "i": "696"}, {"t": 0, "n": "ראש הנקרה", "i": "1138"}, {"t": 90, "n": "מכמורת", "i": "750"}, {"t": 45, "n": "גלאון", "i": "329"}, {"t": 60, "n": "תמרת", "i": "1296"}, {"t": 90, "n": "מעלה אדומים", "i": "778"}, {"t": 90, "n": "פארן", "i": "1046"}, {"t": 60, "n": "שלוחות", "i": "1242"}, {"t": 15, "n": "כרם שלום", "i": "661"}, {"t": 90, "n": "אל עמארני, אל מסק", "i": "1381"}, {"t": 60, "n": "מרחביה מושב", "i": "810"}, {"t": 90, "n": "נטעים", "i": "892"}, {"t": 30, "n": "מעגלים, גבעולים, מלילות", "i": "1317"}, {"t": 60, "n": "גבע כרמל", "i": "286"}, {"t": 90, "n": "שילת", "i": "1239"}, {"t": 60, "n": "טירת צבי", "i": "486"}, {"t": 60, "n": "דבוריה", "i": "359"}, {"t": 90, "n": "כפר הנוער קריית יערים", "i": "1429"}, {"t": 30, "n": "בית שקמה", "i": "230"}, {"t": 90, "n": "ערד", "i": "1039"}, {"t": 90, "n": "ברקאי", "i": "263"}, {"t": 90, "n": "גני יוחנן", "i": "346"}, {"t": 90, "n": "רמת הנדיב", "i": "1175"}, {"t": 90, "n": "מרכז אזורי מגילות", "i": "1356"}, {"t": 60, "n": "ראס אל-עין", "i": "1136"}, {"t": 30, "n": "ינוח ג'ת", "i": "521"}, {"t": 90, "n": "גבעת ברנר", "i": "292"}, {"t": 90, "n": "סלעית", "i": "945"}, {"t": 90, "n": "גלגל", "i": "330"}, {"t": 90, "n": "שני ליבנה", "i": "1249"}, {"t": 60, "n": "זרזיר", "i": "422"}, {"t": 15, "n": "נאות גולן", "i": "840"}, {"t": 90, "n": "רעננה", "i": "1185"}, {"t": 30, "n": "נגבה", "i": "847"}, {"t": 60, "n": "כפר מנדא", "i": "630"}, {"t": 0, "n": "יערה", "i": "528"}, {"t": 0, "n": "אלקוש", "i": "125"}, {"t": 30, "n": "רפטינג נהר הירדן", "i": "2182"}, {"t": 90, "n": "כפר אלדד", "i": "583"}, {"t": 90, "n": "יקום", "i": "536"}, {"t": 90, "n": "פדיה", "i": "1051"}, {"t": 90, "n": "חוות ערנדל", "i": "435"}, {"t": 15, "n": "גבים, מכללת ספיר", "i": "283"}, {"t": 60, "n": "אזור תעשייה תרדיון", "i": "78"}, {"t": 60, "n": "בית ירח", "i": "25"}, {"t": 60, "n": "גבעת וולפסון", "i": "294"}, {"t": 15, "n": "עין יעקב", "i": "1001"}, {"t": 90, "n": "אלמוג", "i": "121"}, {"t": 60, "n": "מנשית זבדה", "i": "759"}, {"t": 90, "n": "עין תמר", "i": "1012"}, {"t": 30, "n": "בית ג'אן", "i": "181"}, {"t": 90, "n": "חבצלת השרון וצוקי ים", "i": "426"}, {"t": 15, "n": "מפלסים", "i": "793"}, {"t": 60, "n": "כפר טבאש", "i": "616"}, {"t": 15, "n": "גשור", "i": "354"}, {"t": 15, "n": "רעים", "i": "1184"}, {"t": 60, "n": "רחוב", "i": "1156"}, {"t": 90, "n": "שורש", "i": "1229"}, {"t": 15, "n": "שמיר", "i": "1246"}, {"t": 60, "n": "יסעור", "i": "525"}, {"t": 60, "n": "בית אורן", "i": "175"}, {"t": 90, "n": "אליקים", "i": "117"}, {"t": 0, "n": "נווה זיו", "i": "861"}, {"t": 90, "n": "גבעון החדשה", "i": "1339"}, {"t": 60, "n": "מגדים", "i": "702"}, {"t": 45, "n": "מתחם בני דרום", "i": "834"}, {"t": 60, "n": "כפר מנחם", "i": "631"}, {"t": 60, "n": "מרחביה קיבוץ", "i": "811"}, {"t": 60, "n": "דברת", "i": "361"}, {"t": 15, "n": "יבול", "i": "496"}, {"t": 30, "n": "ערב אל נעים", "i": "1037"}, {"t": 60, "n": "כפר חיטים", "i": "611"}, {"t": 60, "n": "כדורי", "i": "555"}, {"t": 60, "n": "שדה נחום", "i": "1209"}, {"t": 60, "n": "רבדים", "i": "1143"}, {"t": 90, "n": "גינתון", "i": "326"}, {"t": 30, "n": "בוסתן הגליל", "i": "165"}, {"t": 60, "n": "בית ניר", "i": "210"}, {"t": 90, "n": "עדי עד", "i": "961"}, {"t": 60, "n": "אשדות יעקב", "i": "147"}, {"t": 90, "n": "גבעת ניל''י", "i": "304"}, {"t": 0, "n": "אבני איתן", "i": "16"}, {"t": 60, "n": "ירדנה", "i": "541"}, {"t": 90, "n": "בארות יצחק", "i": "162"}, {"t": 30, "n": "משען", "i": "833"}, {"t": 45, "n": "ורדון", "i": "411"}, {"t": 90, "n": "כפר אוריה", "i": "581"}, {"t": 90, "n": "באר אורה", "i": "157"}, {"t": 60, "n": "נווה ים", "i": "863"}, {"t": 0, "n": "נטור", "i": "890"}, {"t": 30, "n": "ניר עקיבא", "i": "911"}, {"t": 60, "n": "כפר חנניה", "i": "613"}, {"t": 90, "n": "גבעת חיים מאוחד", "i": "299"}, {"t": 90, "n": "אחיסמך", "i": "85"}, {"t": 60, "n": "לביא", "i": "671"}, {"t": 90, "n": "אודים", "i": "23"}, {"t": 90, "n": "עזריאל", "i": "972"}, {"t": 90, "n": "אזור תעשייה אפק ולב הארץ", "i": "44"}, {"t": 90, "n": "רמות מאיר", "i": "1169"}, {"t": 30, "n": "מירון", "i": "745"}, {"t": 90, "n": "אחיעזר", "i": "86"}, {"t": 90, "n": "שילה", "i": "1238"}, {"t": 60, "n": "עספיא", "i": "1031"}, {"t": 0, "n": "מרגליות", "i": "807"}, {"t": 90, "n": "ריחן", "i": "1161"}, {"t": 60, "n": "חוואלד", "i": "1415"}, {"t": 45, "n": "רנן", "i": "1183"}, {"t": 90, "n": "בית סוהר השרון", "i": "212"}, {"t": 30, "n": "שרשרת", "i": "1268"}, {"t": 90, "n": "אזור תעשייה אריאל", "i": "1401"}, {"t": 45, "n": "אל עזי", "i": "99"}, {"t": 90, "n": "זנוח", "i": "420"}, {"t": 90, "n": "נחשון", "i": "887"}, {"t": 90, "n": "ינוב", "i": "520"}, {"t": 60, "n": "חמדיה", "i": "456"}, {"t": 90, "n": "שושנת העמקים", "i": "1231"}, {"t": 90, "n": "אזור תעשייה רגבים", "i": "71"}, {"t": 90, "n": "בית ספר אורט בנימינה", "i": "216"}, {"t": 15, "n": "ניר עם", "i": "909"}, {"t": 60, "n": "כפר גדעון", "i": "590"}, {"t": 0, "n": "מעיין ברוך", "i": "775"}, {"t": 90, "n": "מגדל עוז", "i": "705"}, {"t": 90, "n": "געש", "i": "350"}, {"t": 90, "n": "שבי שומרון", "i": "1195"}, {"t": 60, "n": "אשחר", "i": "148"}, {"t": 0, "n": "מעיליא", "i": "777"}, {"t": 90, "n": "משמר איילון", "i": "824"}, {"t": 30, "n": "אמנון", "i": "129"}, {"t": 60, "n": "כפר מצר", "i": "628"}, {"t": 60, "n": "כפר המכבי", "i": "598"}, {"t": 60, "n": "עדי", "i": "960"}, {"t": 45, "n": "סגולה", "i": "938"}, {"t": 60, "n": "קדרון", "i": "1102"}, {"t": 90, "n": "אפרת", "i": "137"}, {"t": 60, "n": "נשר", "i": "929"}, {"t": 90, "n": "כפר פינס", "i": "644"}, {"t": 60, "n": "שרונה", "i": "1265"}, {"t": 15, "n": "חוף כורסי, לבנון, חלוקים", "i": "1422"}, {"t": 60, "n": "בית קשת", "i": "225"}, {"t": 45, "n": "זבדיאל", "i": "412"}, {"t": 90, "n": "עבדת", "i": "956"}, {"t": 60, "n": "שומריה", "i": "1226"}, {"t": 15, "n": "מגן", "i": "710"}, {"t": 90, "n": "אבו קרינאת", "i": "4"}, {"t": 60, "n": "כלא דמון", "i": "569"}, {"t": 60, "n": "בית גוברין", "i": "182"}, {"t": 0, "n": "אודם", "i": "24"}, {"t": 90, "n": "גמזו", "i": "332"}, {"t": 90, "n": "עדנים", "i": "962"}, {"t": 45, "n": "רהט", "i": "1148"}, {"t": 60, "n": "קריית טבעון - בית זייד", "i": "1121"}, {"t": 60, "n": "גבת", "i": "312"}, {"t": 0, "n": "כרם בן זמרה", "i": "659"}, {"t": 15, "n": "מבטחים, עמיעוז, ישע", "i": "1316"}, {"t": 30, "n": "צמח", "i": "1445"}, {"t": 60, "n": "סנדלה", "i": "948"}, {"t": 90, "n": "טירה", "i": "483"}, {"t": 45, "n": "מסלול", "i": "764"}, {"t": 90, "n": "נריה", "i": "928"}, {"t": 15, "n": "יחיעם", "i": "516"}, {"t": 90, "n": "מצדה", "i": "794"}, {"t": 90, "n": "מרכז אזורי דרום השרון", "i": "1350"}, {"t": 90, "n": "יהל", "i": "509"}, {"t": 60, "n": "בית שערים", "i": "229"}, {"t": 60, "n": "אשדות יעקב", "i": "146"}, {"t": 45, "n": "להב", "i": "673"}, {"t": 30, "n": "שזור", "i": "1232"}, {"t": 30, "n": "גיאה", "i": "321"}, {"t": 90, "n": "ברוכין", "i": "257"}, {"t": 30, "n": "כרכום", "i": "656"}, {"t": 15, "n": "כפר חרוב", "i": "615"}, {"t": 0, "n": "ערב אל עראמשה", "i": "1038"}, {"t": 0, "n": "נווה אטי''ב", "i": "856"}, {"t": 90, "n": "אזור תעשייה ברקן", "i": "1402"}, {"t": 30, "n": "שדה דוד", "i": "1203"}, {"t": 90, "n": "קסר א-סר", "i": "1115"}, {"t": 90, "n": "ארגמן", "i": "139"}, {"t": 15, "n": "נירים", "i": "913"}, {"t": 90, "n": "אלעזר", "i": "123"}, {"t": 90, "n": "חיננית", "i": "452"}, {"t": 60, "n": "יודפת", "i": "512"}, {"t": 90, "n": "שער מנשה", "i": "1257"}, {"t": 90, "n": "קריית אונו", "i": "1118"}, {"t": 90, "n": "קציר", "i": "1114"}, {"t": 45, "n": "צומת דבירה", "i": "1442"}, {"t": 60, "n": "כפר הרי''ף וצומת ראם", "i": "604"}, {"t": 30, "n": "שדה יואב", "i": "1205"}, {"t": 90, "n": "כרמל", "i": "669"}, {"t": 60, "n": "שדה אילן", "i": "1199"}, {"t": 30, "n": "אור הגנוז", "i": "31"}, {"t": 90, "n": "פורת", "i": "1056"}, {"t": 60, "n": "מוקיבלה", "i": "728"}, {"t": 60, "n": "משגב דב", "i": "818"}, {"t": 60, "n": "זכריה", "i": "417"}, {"t": 30, "n": "בית העלמין החדש נהריה", "i": "1411"}, {"t": 15, "n": "שדרות, איבים", "i": "1221"}, {"t": 30, "n": "אשקלון - דרום", "i": "6037"}, {"t": 30, "n": "אשקלון - צפון", "i": "6039"}, {"t": 0, "n": "סער", "i": "951"}, {"t": 90, "n": "נאות הכיכר", "i": "841"}, {"t": 60, "n": "קורנית", "i": "1106"}, {"t": 90, "n": "רינתיה", "i": "1164"}, {"t": 30, "n": "ברור חיל", "i": "258"}, {"t": 45, "n": "משמר הנגב", "i": "827"}, {"t": 30, "n": "בית הגדי", "i": "185"}, {"t": 90, "n": "בית זית", "i": "192"}, {"t": 15, "n": "עין הבשור", "i": "987"}, {"t": 90, "n": "עין יהב", "i": "1000"}, {"t": 90, "n": "אשלים", "i": "151"}, {"t": 60, "n": "קבוצת גבע", "i": "284"}, {"t": 30, "n": "ברחבי הארץ", "i": "1390"}, {"t": 0, "n": "דפנה", "i": "378"}, {"t": 90, "n": "מודיעין עילית", "i": "719"}, {"t": 60, "n": "מורן", "i": "729"}, {"t": 60, "n": "בית חלקיה", "i": "197"}, {"t": 90, "n": "ג'סר א-זרקא", "i": "276"}, {"t": 90, "n": "אלון", "i": "104"}, {"t": 0, "n": "צוריאל", "i": "1085"}, {"t": 90, "n": "חוות גלעד", "i": "1366"}, {"t": 90, "n": "מזכרת בתיה", "i": "732"}, {"t": 90, "n": "שדה בר", "i": "436"}, {"t": 15, "n": "בני יהודה וגבעת יואב", "i": "1309"}, {"t": 0, "n": "חניתה", "i": "461"}, {"t": 90, "n": "מגשימים", "i": "713"}, {"t": 30, "n": "אחוזם", "i": "80"}, {"t": 30, "n": "כישור", "i": "568"}, {"t": 60, "n": "שלפים", "i": "1245"}, {"t": 60, "n": "נין", "i": "895"}, {"t": 15, "n": "עלומים", "i": "1018"}, {"t": 90, "n": "חשמונאים", "i": "477"}, {"t": 60, "n": "נווה מבטח", "i": "866"}, {"t": 45, "n": "אזור תעשייה קריית גת", "i": "1358"}, {"t": 60, "n": "כפר זוהרים", "i": "608"}, {"t": 60, "n": "בן זכאי", "i": "234"}, {"t": 90, "n": "משאבי שדה", "i": "817"}, {"t": 60, "n": "נצרת", "i": "926"}, {"t": 90, "n": "עידן", "i": "976"}, {"t": 45, "n": "נועם", "i": "869"}, {"t": 90, "n": "איתמר", "i": "95"}, {"t": 60, "n": "יפעת", "i": "532"}, {"t": 90, "n": "אזור תעשייה שחק", "i": "1409"}, {"t": 90, "n": "ערערה בנגב", "i": "1041"}, {"t": 30, "n": "מעגלים, גבעולים, מלילות", "i": "1318"}, {"t": 90, "n": "באר יעקב", "i": "160"}, {"t": 90, "n": "גנות", "i": "342"}, {"t": 0, "n": "מיצר", "i": "743"}, {"t": 60, "n": "קבוצת יבנה", "i": "1095"}, {"t": 90, "n": "בני ברק", "i": "237"}, {"t": 60, "n": "יערות הכרמל", "i": "529"}, {"t": 90, "n": "כסלון", "i": "576"}, {"t": 0, "n": "בית ספר שדה מירון", "i": "217"}, {"t": 45, "n": "אזור תעשייה באר טוביה", "i": "1359"}, {"t": 90, "n": "בית יתיר", "i": "206"}, {"t": 30, "n": "שבי דרום", "i": "1193"}, {"t": 90, "n": "מתחם \"חנה וסע\" שפיים", "i": "1436"}, {"t": 45, "n": "חצור", "i": "467"}, {"t": 0, "n": "מג'דל שמס", "i": "701"}, {"t": 15, "n": "זמרת, שובה", "i": "419"}, {"t": 45, "n": "ערוגות", "i": "1040"}, {"t": 60, "n": "מאיר שפיה", "i": "689"}, {"t": 60, "n": "עשרת", "i": "1043"}, {"t": 90, "n": "נילי", "i": "894"}, {"t": 90, "n": "בצרה", "i": "251"}, {"t": 60, "n": "ניר דוד", "i": "903"}, {"t": 30, "n": "שדה אליעזר", "i": "1201"}, {"t": 60, "n": "נחושה", "i": "879"}, {"t": 90, "n": "מלון סיקס סנסס שחרות", "i": "2196"}, {"t": 15, "n": "כפר עזה", "i": "642"}, {"t": 60, "n": "חנתון", "i": "462"}, {"t": 30, "n": "זרועה", "i": "421"}, {"t": 90, "n": "כפר רות", "i": "649"}, {"t": 60, "n": "חג'אג'רה", "i": "428"}, {"t": 90, "n": "תחנת רכבת ראש העין", "i": "1351"}, {"t": 60, "n": "אשכולות", "i": "149"}, {"t": 90, "n": "תנובות", "i": "1297"}, {"t": 90, "n": "כרמי צור", "i": "663"}, {"t": 90, "n": "מרכז ימי קיסריה", "i": "814"}, {"t": 60, "n": "חוסנייה", "i": "443"}, {"t": 90, "n": "עלמון", "i": "1022"}, {"t": 60, "n": "תל יוסף", "i": "1280"}, {"t": 90, "n": "מתן", "i": "837"}, {"t": 90, "n": "תעשיון חצב", "i": "1299"}, {"t": 90, "n": "חרמש", "i": "474"}, {"t": 60, "n": "אזור תעשייה גדרה", "i": "1403"}, {"t": 30, "n": "כמון", "i": "402"}, {"t": 90, "n": "סביון", "i": "937"}, {"t": 0, "n": "מסעדה", "i": "765"}, {"t": 0, "n": "דוב''ב", "i": "364"}, {"t": 90, "n": "כפר עבודה", "i": "641"}, {"t": 90, "n": "מרחצאות עין גדי", "i": "812"}, {"t": 60, "n": "רביד", "i": "1145"}, {"t": 60, "n": "מצפה נטופה", "i": "802"}, {"t": 30, "n": "פרוד", "i": "1069"}, {"t": 30, "n": "ברכיה", "i": "261"}, {"t": 30, "n": "יסוד המעלה", "i": "523"}, {"t": 60, "n": "מסילות", "i": "762"}, {"t": 60, "n": "דגניה ב", "i": "363"}, {"t": 60, "n": "בית רימון", "i": "226"}, {"t": 90, "n": "אורנית", "i": "40"}, {"t": 90, "n": "מעון", "i": "772"}, {"t": 0, "n": "יראון", "i": "540"}, {"t": 60, "n": "בית שאן", "i": "227"}, {"t": 90, "n": "אלוני יצחק", "i": "110"}, {"t": 60, "n": "אזור תעשייה צבאים", "i": "66"}, {"t": 45, "n": "אשדוד - איזור תעשייה צפוני", "i": "1386"}, {"t": 90, "n": "רמת הכובש", "i": "1174"}, {"t": 60, "n": "כעביה", "i": "577"}, {"t": 15, "n": "כיסופים", "i": "566"}, {"t": 60, "n": "יובלים", "i": "511"}, {"t": 60, "n": "מגדל", "i": "703"}, {"t": 60, "n": "גאליה", "i": "281"}, {"t": 90, "n": "חבצלת השרון וצוקי ים", "i": "1312"}, {"t": 90, "n": "כפר ביל''ו", "i": "585"}, {"t": 60, "n": "הודיות", "i": "387"}, {"t": 90, "n": "נעלה", "i": "920"}, {"t": 90, "n": "משמרת", "i": "832"}, {"t": 90, "n": "אחיה", "i": "82"}, {"t": 0, "n": "לב החולה", "i": "1433"}, {"t": 60, "n": "טבריה", "i": "478"}, {"t": 60, "n": "נופית", "i": "874"}, {"t": 90, "n": "חמדת", "i": "457"}, {"t": 90, "n": "עין השופט", "i": "993"}, {"t": 90, "n": "ישרש", "i": "550"}, {"t": 60, "n": "חוקוק", "i": "445"}, {"t": 90, "n": "מודיעין מכבים רעות", "i": "716"}, {"t": 60, "n": "בית סוהר קישון", "i": "1380"}, {"t": 90, "n": "חולדה", "i": "438"}, {"t": 15, "n": "יתד", "i": "551"}, {"t": 90, "n": "נעמה", "i": "921"}, {"t": 60, "n": "מרכז חבר", "i": "1328"}, {"t": 60, "n": "יבנה", "i": "499"}, {"t": 15, "n": "עמיר", "i": "1027"}, {"t": 90, "n": "עשהאל", "i": "1364"}, {"t": 60, "n": "שדי תרומות", "i": "1217"}, {"t": 30, "n": "בר יוחאי", "i": "256"}, {"t": 15, "n": "גונן", "i": "316"}, {"t": 90, "n": "מצפה שלם", "i": "804"}, {"t": 90, "n": "שחרות", "i": "1234"}, {"t": 90, "n": "עזריה", "i": "973"}, {"t": 45, "n": "עין צורים", "i": "1007"}, {"t": 90, "n": "מתחם פי גלילות", "i": "1357"}, {"t": 0, "n": "כברי", "i": "554"}, {"t": 90, "n": "טללים", "i": "490"}, {"t": 90, "n": "נוף איילון", "i": "870"}, {"t": 90, "n": "פרדסיה", "i": "1068"}, {"t": 90, "n": "דליה", "i": "373"}, {"t": 90, "n": "נווה ירק", "i": "865"}, {"t": 90, "n": "מבואות יריחו", "i": "695"}, {"t": 15, "n": "זיקים", "i": "414"}, {"t": 60, "n": "אורנים", "i": "39"}, {"t": 30, "n": "יד נתן", "i": "506"}, {"t": 30, "n": "לבון", "i": "670"}, {"t": 60, "n": "דמיידה", "i": "376"}, {"t": 0, "n": "חורפיש", "i": "447"}, {"t": 90, "n": "הרצליה - מרכז וגליל ים", "i": "1310"}, {"t": 60, "n": "קריית מוצקין", "i": "1124"}, {"t": 30, "n": "שיבולים", "i": "1235"}, {"t": 60, "n": "בני עי''ש", "i": "244"}, {"t": 45, "n": "קריית מלאכי", "i": "1125"}, {"t": 30, "n": "תל קציר", "i": "1285"}, {"t": 0, "n": "מלכיה", "i": "752"}, {"t": 60, "n": "שקף", "i": "1264"}, {"t": 90, "n": "בית מאיר", "i": "208"}, {"t": 90, "n": "אליכין", "i": "114"}, {"t": 60, "n": "מרכז חבר", "i": "1342"}, {"t": 60, "n": "שעב", "i": "1251"}, {"t": 90, "n": "גאולים", "i": "280"}, {"t": 60, "n": "אום אלג'נם", "i": "26"}, {"t": 15, "n": "יד מרדכי", "i": "505"}, {"t": 90, "n": "ורד יריחו", "i": "410"}, {"t": 30, "n": "כפר שמאי", "i": "650"}, {"t": 30, "n": "פטיש", "i": "1057"}, {"t": 90, "n": "צובה", "i": "1075"}, {"t": 15, "n": "שעל", "i": "1252"}, {"t": 60, "n": "בית סוהר צלמון", "i": "1383"}, {"t": 90, "n": "בת חן", "i": "268"}, {"t": 30, "n": "גדות", "i": "313"}, {"t": 45, "n": "בית קמה", "i": "224"}, {"t": 60, "n": "כפר זיתים", "i": "609"}, {"t": 60, "n": "בני ראם", "i": "246"}, {"t": 45, "n": "תימורים", "i": "1277"}, {"t": 90, "n": "עין בוקק", "i": "983"}, {"t": 0, "n": "נוב", "i": "852"}, {"t": 15, "n": "עברון", "i": "957"}, {"t": 45, "n": "כפר ורבורג", "i": "606"}, {"t": 0, "n": "אפיק", "i": "134"}, {"t": 60, "n": "רקפת", "i": "1186"}, {"t": 60, "n": "עין חרוד", "i": "999"}, {"t": 90, "n": "בית עלמין מורשה", "i": "1413"}, {"t": 90, "n": "בית נחמיה", "i": "209"}, {"t": 15, "n": "כפר סאלד", "i": "637"}, {"t": 30, "n": "כליל", "i": "570"}, {"t": 90, "n": "אזור תעשייה מיתרים", "i": "59"}, {"t": 0, "n": "אל רום", "i": "101"}, {"t": 90, "n": "כפר חב''ד", "i": "610"}, {"t": 90, "n": "אביאל", "i": "6"}, {"t": 60, "n": "אזור תעשייה ציפורית", "i": "1363"}, {"t": 90, "n": "ברקן", "i": "264"}, {"t": 90, "n": "טלמון", "i": "491"}, {"t": 90, "n": "בית חשמונאי", "i": "201"}, {"t": 30, "n": "אשרת", "i": "153"}, {"t": 15, "n": "חוף כינר, דוגה, דוגית", "i": "1423"}, {"t": 90, "n": "איירפורט סיטי", "i": "1410"}, {"t": 30, "n": "דורות", "i": "367"}, {"t": 90, "n": "בית אל", "i": "176"}, {"t": 30, "n": "משמר הירדן", "i": "826"}, {"t": 90, "n": "עין החורש", "i": "989"}, {"t": 90, "n": "בית שמש", "i": "228"}, {"t": 60, "n": "בית סוהר שיטה וגלבוע", "i": "215"}, {"t": 0, "n": "שדה נחמיה", "i": "1210"}, {"t": 60, "n": "באר מילכה", "i": "161"}, {"t": 60, "n": "רם און", "i": "1166"}, {"t": 30, "n": "כרמיאל", "i": "665"}, {"t": 90, "n": "פרדס חנה כרכור", "i": "1067"}, {"t": 90, "n": "נופך", "i": "875"}, {"t": 90, "n": "עמיחי", "i": "1347"}, {"t": 60, "n": "גן נר", "i": "338"}, {"t": 30, "n": "חצור הגלילית", "i": "468"}, {"t": 90, "n": "צופית", "i": "1078"}, {"t": 90, "n": "אורה", "i": "35"}, {"t": 90, "n": "לטרון", "i": "682"}, {"t": 90, "n": "עין שריד", "i": "1011"}, {"t": 90, "n": "יהוד מונוסון", "i": "508"}, {"t": 60, "n": "עופר", "i": "967"}, {"t": 60, "n": "ינון", "i": "522"}, {"t": 90, "n": "סוסיא", "i": "941"}, {"t": 15, "n": "חוף זיקים", "i": "1421"}, {"t": 90, "n": "נאות קדומים", "i": "1437"}, {"t": 90, "n": "גן השומרון", "i": "334"}, {"t": 45, "n": "תפרח", "i": "1301"}, {"t": 90, "n": "קדומים", "i": "1096"}, {"t": 60, "n": "חפץ חיים", "i": "464"}, {"t": 90, "n": "אבני חפץ", "i": "17"}, {"t": 90, "n": "עץ אפרים", "i": "1034"}, {"t": 90, "n": "מרעית", "i": "556"}, {"t": 45, "n": "קריית גת, כרמי גת", "i": "1120"}, {"t": 90, "n": "ראש העין", "i": "1139"}, {"t": 90, "n": "יקנעם עילית", "i": "539"}, {"t": 90, "n": "רבבה", "i": "1142"}, {"t": 30, "n": "כמאנה", "i": "1450"}, {"t": 90, "n": "חגלה", "i": "430"}, {"t": 0, "n": "אלוני הבשן", "i": "109"}, {"t": 60, "n": "גן הדרום", "i": "333"}, {"t": 0, "n": "נטועה", "i": "889"}, {"t": 60, "n": "טפחות", "i": "495"}, {"t": 0, "n": "גורן", "i": "317"}, {"t": 60, "n": "יזרעאל", "i": "515"}, {"t": 60, "n": "הסוללים", "i": "396"}, {"t": 90, "n": "מתתיהו", "i": "839"}, {"t": 60, "n": "מעלה גלבוע", "i": "780"}, {"t": 90, "n": "גבעת חיים איחוד", "i": "298"}, {"t": 90, "n": "טל שחר", "i": "489"}, {"t": 45, "n": "משואות יצחק", "i": "822"}, {"t": 0, "n": "אזור תעשייה רמת דלתון", "i": "73"}, {"t": 90, "n": "מצר", "i": "805"}, {"t": 90, "n": "גבעת עדה", "i": "305"}, {"t": 30, "n": "שלווה", "i": "1241"}, {"t": 90, "n": "ג'ת", "i": "278"}, {"t": 60, "n": "בניה", "i": "247"}, {"t": 60, "n": "עין הנצי''ב", "i": "991"}, {"t": 90, "n": "קלנסווה", "i": "1112"}, {"t": 60, "n": "גזית", "i": "319"}, {"t": 45, "n": "ניצן", "i": "896"}, {"t": 90, "n": "אריאל", "i": "141"}, {"t": 30, "n": "ירכא", "i": "544"}, {"t": 60, "n": "שמשית", "i": "1248"}, {"t": 45, "n": "מרכז שפירא", "i": "816"}, {"t": 90, "n": "גלעד", "i": "331"}, {"t": 15, "n": "אור הנר", "i": "32"}, {"t": 90, "n": "אייל", "i": "88"}, {"t": 30, "n": "נהורה", "i": "849"}, {"t": 60, "n": "אחיהוד", "i": "83"}, {"t": 60, "n": "תחנת רכבת כפר יהושוע", "i": "1353"}, {"t": 0, "n": "גורנות הגליל", "i": "318"}, {"t": 15, "n": "בארי", "i": "164"}, {"t": 60, "n": "אלון הגליל", "i": "105"}, {"t": 60, "n": "מצפה אבי''ב", "i": "799"}, {"t": 90, "n": "קרני שומרון", "i": "1133"}, {"t": 15, "n": "כנף", "i": "574"}, {"t": 45, "n": "תארבין", "i": "1305"}, {"t": 90, "n": "גן חיים", "i": "335"}, {"t": 90, "n": "גן יאשיה", "i": "336"}, {"t": 90, "n": "אזור תעשייה רגמ", "i": "1408"}, {"t": 90, "n": "נווה אילן", "i": "857"}, {"t": 60, "n": "רוויה", "i": "1150"}, {"t": 0, "n": "שומרה", "i": "1225"}, {"t": 90, "n": "כפר חיים", "i": "612"}]